task_stats_pkg/__init__.py
task_stats_pkg/task_stats.py
taskapp_status_pkg_ash93-0.0.1.dist-info/LICENSE
taskapp_status_pkg_ash93-0.0.1.dist-info/METADATA
taskapp_status_pkg_ash93-0.0.1.dist-info/WHEEL
taskapp_status_pkg_ash93-0.0.1.dist-info/top_level.txt
taskapp_status_pkg_ash93-0.0.1.dist-info/RECORD
