Metadata-Version: 2.1
Name: taskapp-status-pkg-ash93
Version: 0.0.1
Summary: package to calculate task stats for the Todo Task app
Home-page: https://github.com/pypa/sampleproject
Author: Ashwini Patil
Author-email: ashwini.patil9304@gmail.com
License: UNKNOWN
Platform: UNKNOWN
Classifier: Programming Language :: Python :: 3
Classifier: License :: OSI Approved :: MIT License
Classifier: Operating System :: OS Independent
Requires-Python: >=3.6
License-File: LICENSE
